{"notifications": [{"type": "notificationTray", "item": {"unreadCount": 0}}], "response": {"friends": {"items": [{"tips": {"count": 3}, "contact": {"twitter": "310_kenji", "facebook": "100002815635132"}, "firstName": "Kenji", "gender": "male", "lastName": "Sato", "id": "14681939", "bio": "60\u6b73\u4ee3\u524d\u534a\u3001\u4f55\u4e8b\u306b\u3082\u30c1\u30e3\u30ec\u30f3\u30b8\u529b\u65fa\u76db\u3002\u8da3\u5473\u3001\u8aad\u66f8\u2022\u65c5\u884c\u3002\u304a\u9152\u5927\u597d\u304d\u3002\u98db\u884c\u6a5f\u5927\u597d\u304dANA\u6d3e\u3002\u5609\u7a42\u9ad8\u2192\u7389\u5ddd\u5927\u5b66Facebook.twitter.blog\u3082\u3084\u3063\u3066\u307e\u3059\u306e\u3067\u5b9c\u3057\u304f\u304a\u9858\u3044\u3057\u307e\u3059\r\nInstagram:310_KENJI", "photo": {"prefix": "https://igx.4sqi.net/img/user/", "suffix": "/H54ELLBIU1QRMHVU.jpg"}, "homeCity": "Iizuka,Fukuoka,Japan", "lists": {"groups": [{"items": [], "count": 2, "type": "created"}]}}, {"tips": {"count": 0}, "contact": {"facebook": "768349050"}, "firstName": "Steve", "gender": "male", "lastName": "Lin", "id": "4648244", "bio": "", "photo": {"prefix": "https://igx.4sqi.net/img/user/", "suffix": "/blank_boy.png", "default": true}, "homeCity": "Singapore", "lists": {"groups": [{"items": [], "count": 2, "type": "created"}]}}, {"tips": {"count": 2}, "contact": {"twitter": "dyosakikay", "facebook": "818234184"}, "firstName": "\ue335\ue327becca", "gender": "female", "lastName": "quiambao\ue327\ue335", "id": "6860087", "bio": "", "photo": {"prefix": "https://igx.4sqi.net/img/user/", "suffix": "/R0ARZ442SVVRTDM0.jpg"}, "homeCity": "Singapore", "lists": {"groups": [{"items": [], "count": 3, "type": "created"}]}}, {"tips": {"count": 0}, "contact": {"twitter": "jacelynmaggie", "facebook": "621099411"}, "firstName": "Jacelyn", "gender": "female", "lastName": "Koh", "id": "6630374", "bio": "", "photo": {"prefix": "https://igx.4sqi.net/img/user/", "suffix": "/2QV35AVWYZ2D2QHN.jpg"}, "homeCity": "Singapore", "lists": {"groups": [{"items": [], "count": 2, "type": "created"}]}}, {"tips": {"count": 5}, "contact": {"facebook": "1397657384"}, "firstName": ">_~", "gender": "male", "lastName": "Wink!!", "id": "3779951", "bio": "", "photo": {"prefix": "https://igx.4sqi.net/img/user/", "suffix": "/A0RMHTEGDO3LKTJ4.jpg"}, "homeCity": "Singapore", "lists": {"groups": [{"items": [], "count": 2, "type": "created"}]}}, {"tips": {"count": 1}, "contact": {"twitter": "lesleysheph", "facebook": "646825849"}, "firstName": "Lesley", "gender": "female", "lastName": "Shepherdson", "id": "4416913", "bio": "", "photo": {"prefix": "https://igx.4sqi.net/img/user/", "suffix": "/blank_girl.png", "default": true}, "homeCity": "Singapore", "lists": {"groups": [{"items": [], "count": 2, "type": "created"}]}}, {"tips": {"count": 0}, "contact": {}, "firstName": "Semut", "gender": "male", "lastName": "Kerengga", "id": "20794469", "bio": "", "photo": {"prefix": "https://igx.4sqi.net/img/user/", "suffix": "/IC5N04UJAC4PVLMS.jpg"}, "homeCity": "Melaka", "lists": {"groups": [{"items": [], "count": 2, "type": "created"}]}}, {"tips": {"count": 0}, "contact": {"twitter": "benny_pan", "facebook": "561459614"}, "firstName": "Yanming", "gender": "male", "lastName": "Pan", "id": "5447350", "bio": "", "photo": {"prefix": "https://igx.4sqi.net/img/user/", "suffix": "/WRDGKDTPWBHUIKRR.jpg"}, "homeCity": "Singapore", "lists": {"groups": [{"items": [], "count": 8, "type": "created"}]}}, {"superuser": 3, "tips": {"count": 40}, "contact": {"twitter": "medicheng", "facebook": "573677657"}, "firstName": "Paul", "gender": "male", "lastName": "Cheng", "id": "1863193", "bio": "I love making friends", "photo": {"prefix": "https://igx.4sqi.net/img/user/", "suffix": "/MVYX22OZI3EMAADG.jpg"}, "homeCity": "Hougang, Singapore", "lists": {"groups": [{"items": [], "count": 9, "type": "created"}]}}, {"tips": {"count": 0}, "contact": {"facebook": "523029817"}, "firstName": "Simon", "gender": "male", "lastName": "Wang", "id": "4031546", "bio": "", "photo": {"prefix": "https://igx.4sqi.net/img/user/", "suffix": "/PWSKBFPH3HZ2K4TB.jpg"}, "homeCity": "Singapore", "lists": {"groups": [{"items": [], "count": 2, "type": "created"}]}}, {"tips": {"count": 0}, "contact": {"facebook": "628866632"}, "firstName": "Tan", "gender": "male", "lastName": "Xiong fu", "id": "4508393", "bio": "", "photo": {"prefix": "https://igx.4sqi.net/img/user/", "suffix": "/3F0GPIDK15LPWULQ.jpg"}, "homeCity": "Singapore", "lists": {"groups": [{"items": [], "count": 2, "type": "created"}]}}, {"tips": {"count": 19}, "contact": {"twitter": "azman_aris", "facebook": "1011981750"}, "firstName": "\u0422\u0430\u043a\u0436\u0435 \u0410\u0441\u043c\u0430\u043d", "gender": "male", "lastName": "\u041c\u043e\u0445\u0434 \u0425\u0430\u0440\u0438\u0441", "id": "3477386", "bio": "", "photo": {"prefix": "https://igx.4sqi.net/img/user/", "suffix": "/3477386-BI0AFKW0P5VNDMCQ.jpg"}, "homeCity": "Catalunya, Spain", "lists": {"groups": [{"items": [], "count": 2, "type": "created"}]}}, {"tips": {"count": 0}, "contact": {"twitter": "dedeirdina", "facebook": "704800757"}, "firstName": "Diana", "gender": "female", "lastName": "Chard", "id": "1704734", "bio": "", "photo": {"prefix": "https://igx.4sqi.net/img/user/", "suffix": "/QTDEPHEAYH4A1WYG.jpg"}, "homeCity": "Singapore", "lists": {"groups": [{"items": [], "count": 2, "type": "created"}]}}, {"tips": {"count": 0}, "contact": {"twitter": "kimiekit", "facebook": "604826347"}, "firstName": "KiMiE", "gender": "female", "lastName": "KiT", "id": "1768048", "bio": "", "photo": {"prefix": "https://igx.4sqi.net/img/user/", "suffix": "/S20TLBELPXGRYJZU.jpg"}, "homeCity": "Queenstown", "lists": {"groups": [{"items": [], "count": 2, "type": "created"}]}}, {"tips": {"count": 2}, "contact": {"facebook": "100000528912179"}, "firstName": "Ah Wei", "gender": "male", "id": "4401257", "bio": "", "photo": {"prefix": "https://igx.4sqi.net/img/user/", "suffix": "/4IQEW1DD10LRFQ2U.jpg"}, "homeCity": "Si Mongkhon, Sai Yok, Kanchanaburi 71150, Thailand", "lists": {"groups": [{"items": [], "count": 2, "type": "created"}]}}, {"tips": {"count": 0}, "contact": {}, "firstName": "becca", "gender": "female", "lastName": "quiambao", "id": "1706374", "bio": "", "photo": {"prefix": "https://igx.4sqi.net/img/user/", "suffix": "/MKRRAYP32CNRKBHJ.jpg"}, "homeCity": "Singapore", "lists": {"groups": [{"items": [], "count": 2, "type": "created"}]}}, {"tips": {"count": 61}, "contact": {"facebook": "588648480"}, "firstName": "Juliet", "gender": "female", "lastName": "Li", "id": "2681616", "bio": "", "photo": {"prefix": "https://igx.4sqi.net/img/user/", "suffix": "/2681616-TJ11M15TVOSMPBTU.jpg"}, "homeCity": "Singapore", "lists": {"groups": [{"items": [], "count": 2, "type": "created"}]}}, {"tips": {"count": 0}, "contact": {}, "firstName": "Ganga", "gender": "male", "id": "31735692", "bio": "", "photo": {"prefix": "https://igx.4sqi.net/img/user/", "suffix": "/350PBL0NKSUML1KN.jpg"}, "homeCity": "Singapore", "lists": {"groups": [{"items": [], "count": 2, "type": "created"}]}}, {"tips": {"count": 0}, "contact": {}, "firstName": "Arema", "gender": "male", "lastName": "Nicolas", "id": "15802632", "bio": "", "photo": {"prefix": "https://igx.4sqi.net/img/user/", "suffix": "/JNQB5K0Y2TLD2R5X.jpg"}, "homeCity": "Bandung, Indonesia", "lists": {"groups": [{"items": [], "count": 2, "type": "created"}]}}, {"tips": {"count": 1}, "contact": {"twitter": "rockerskasiakoe", "facebook": "649868370"}, "firstName": "Erning", "gender": "male", "lastName": "Gutierrez", "id": "15828312", "bio": "Arkitekto.Badmintonero.Basketbolero.Pilipino", "photo": {"prefix": "https://igx.4sqi.net/img/user/", "suffix": "/15828312-GFODQAYWUAICZPNY.jpg"}, "homeCity": "Singapore", "lists": {"groups": [{"items": [], "count": 2, "type": "created"}]}}, {"tips": {"count": 0}, "contact": {"facebook": "1019715841"}, "firstName": "Liwei", "gender": "female", "lastName": "Fang", "id": "5154725", "bio": "", "photo": {"prefix": "https://igx.4sqi.net/img/user/", "suffix": "/EA0UHSNNBTXPNPSD.jpg"}, "homeCity": "Singapore", "lists": {"groups": [{"items": [], "count": 2, "type": "created"}]}}, {"tips": {"count": 0}, "contact": {}, "firstName": "Cherie", "gender": "none", "id": "7076755", "bio": "", "photo": {"prefix": "https://igx.4sqi.net/img/user/", "suffix": "/blank_boy.png", "default": true}, "homeCity": "Singapore", "lists": {"groups": [{"items": [], "count": 2, "type": "created"}]}}, {"tips": {"count": 3}, "contact": {"facebook": "681042217"}, "firstName": "Yuchun", "gender": "female", "lastName": "Zhou", "id": "4250653", "bio": "", "photo": {"prefix": "https://igx.4sqi.net/img/user/", "suffix": "/SAFDYK0HP3UELIRD.jpg"}, "homeCity": "Singapore", "lists": {"groups": [{"items": [], "count": 2, "type": "created"}]}}, {"tips": {"count": 1}, "contact": {}, "firstName": "William", "gender": "male", "lastName": "Loo", "id": "5285165", "bio": "", "photo": {"prefix": "https://igx.4sqi.net/img/user/", "suffix": "/OWZVRHIPHZHTNA22.jpg"}, "homeCity": "Singapore", "lists": {"groups": [{"items": [], "count": 2, "type": "created"}]}}, {"tips": {"count": 0}, "contact": {}, "firstName": "Marcus", "gender": "male", "lastName": "Seng", "id": "5637216", "bio": "", "photo": {"prefix": "https://igx.4sqi.net/img/user/", "suffix": "/K4A2YBDOURJMLUUD.jpg"}, "homeCity": "Singapore", "lists": {"groups": [{"items": [], "count": 2, "type": "created"}]}}, {"tips": {"count": 0}, "contact": {}, "firstName": "jacqurine", "gender": "female", "lastName": "quah", "id": "3661818", "bio": "", "photo": {"prefix": "https://igx.4sqi.net/img/user/", "suffix": "/BRVCKGMPUE3XPCAK.jpg"}, "homeCity": "Singapore", "lists": {"groups": [{"items": [], "count": 2, "type": "created"}]}}, {"tips": {"count": 0}, "contact": {"facebook": "1587685845"}, "firstName": "Lissa", "gender": "female", "lastName": "Goh", "id": "4926038", "bio": "", "photo": {"prefix": "https://igx.4sqi.net/img/user/", "suffix": "/TDIVKLYBE25XA1GL.jpg"}, "homeCity": "Singapore", "lists": {"groups": [{"items": [], "count": 2, "type": "created"}]}}, {"tips": {"count": 0}, "contact": {"facebook": "794914125"}, "firstName": "Irene", "gender": "female", "lastName": "Long", "id": "5093046", "bio": "", "photo": {"prefix": "https://igx.4sqi.net/img/user/", "suffix": "/0WXKUNAYYUJBNJZR.jpg"}, "homeCity": "Singapore", "lists": {"groups": [{"items": [], "count": 2, "type": "created"}]}}, {"tips": {"count": 0}, "contact": {"facebook": "708453595"}, "firstName": "Nurul", "gender": "female", "lastName": "Balkis", "id": "3479219", "bio": "", "photo": {"prefix": "https://igx.4sqi.net/img/user/", "suffix": "/HO3WBVTEX5WHQZLV.jpg"}, "homeCity": "Singapore", "lists": {"groups": [{"items": [], "count": 2, "type": "created"}]}}, {"tips": {"count": 0}, "contact": {"facebook": "706645287"}, "firstName": "Jamie", "gender": "female", "lastName": "See", "id": "3321616", "bio": "", "photo": {"prefix": "https://igx.4sqi.net/img/user/", "suffix": "/1W4CBMPKQPQ1X0BH.jpg"}, "homeCity": "Singapore", "lists": {"groups": [{"items": [], "count": 2, "type": "created"}]}}, {"tips": {"count": 0}, "contact": {"twitter": "yandied", "facebook": "1333352767"}, "firstName": "Yandie", "gender": "male", "lastName": "Drzslm", "id": "3347583", "bio": "", "photo": {"prefix": "https://igx.4sqi.net/img/user/", "suffix": "/O4VMFGZLN0VZXUSR.jpg"}, "homeCity": "Palembang, Indonesia", "lists": {"groups": [{"items": [], "count": 2, "type": "created"}]}}, {"tips": {"count": 6}, "contact": {"facebook": "755644352"}, "firstName": "Peggy", "gender": "female", "lastName": "Chan", "id": "14940610", "bio": "", "photo": {"prefix": "https://igx.4sqi.net/img/user/", "suffix": "/14940610-J1PSVJFMQFDFM4ED.jpg"}, "homeCity": "Singapore", "lists": {"groups": [{"items": [], "count": 7, "type": "created"}]}}, {"tips": {"count": 10}, "contact": {"facebook": "1043487033"}, "firstName": "Lydia", "gender": "female", "lastName": "Elmi", "id": "2037363", "bio": "", "photo": {"prefix": "https://igx.4sqi.net/img/user/", "suffix": "/R0GBCV3DNUGCVEU5.jpg"}, "homeCity": "Singapore", "lists": {"groups": [{"items": [], "count": 2, "type": "created"}]}}, {"tips": {"count": 1}, "contact": {"facebook": "533054997"}, "firstName": "Fiza", "gender": "female", "lastName": "Othman", "id": "3892559", "bio": "", "photo": {"prefix": "https://igx.4sqi.net/img/user/", "suffix": "/1IFWJT1AXL0M5TOV.jpg"}, "homeCity": "Singapore", "lists": {"groups": [{"items": [], "count": 2, "type": "created"}]}}, {"tips": {"count": 0}, "contact": {"facebook": "569529459"}, "firstName": "Jacquelyn", "gender": "none", "lastName": "Cheong", "id": "32782485", "bio": "", "photo": {"prefix": "https://igx.4sqi.net/img/user/", "suffix": "/CH2AS0FNGMJ5UGE3.jpg"}, "homeCity": "everywhere", "lists": {"groups": [{"items": [], "count": 2, "type": "created"}]}}, {"tips": {"count": 0}, "contact": {}, "firstName": "Lex", "gender": "male", "lastName": "Chong", "id": "23390393", "bio": "", "photo": {"prefix": "https://igx.4sqi.net/img/user/", "suffix": "/blank_boy.png", "default": true}, "homeCity": "New York, NY", "lists": {"groups": [{"items": [], "count": 2, "type": "created"}]}}, {"tips": {"count": 0}, "contact": {"facebook": "575549208"}, "firstName": "Emma", "gender": "male", "lastName": "Bee", "id": "6263323", "bio": "", "photo": {"prefix": "https://igx.4sqi.net/img/user/", "suffix": "/KQ2MN2XJJZYEIGHC.jpg"}, "homeCity": "Singapore", "lists": {"groups": [{"items": [], "count": 2, "type": "created"}]}}, {"tips": {"count": 0}, "contact": {"facebook": "873035180"}, "firstName": "James", "gender": "male", "lastName": "Ong", "id": "7199361", "bio": "", "photo": {"prefix": "https://igx.4sqi.net/img/user/", "suffix": "/2PHJG4XWKBTYOMKB.jpg"}, "homeCity": "Singapore", "lists": {"groups": [{"items": [], "count": 2, "type": "created"}]}}, {"tips": {"count": 0}, "contact": {"facebook": "747899514"}, "firstName": "Venus", "gender": "female", "lastName": "Cheung", "id": "12313078", "bio": "", "photo": {"prefix": "https://igx.4sqi.net/img/user/", "suffix": "/OWHC2PYMSU01X5N3.jpg"}, "homeCity": "Hong Kong", "lists": {"groups": [{"items": [], "count": 2, "type": "created"}]}}, {"tips": {"count": 0}, "contact": {"facebook": "1226264046"}, "firstName": "Seh", "gender": "female", "lastName": "Alice", "id": "5658256", "bio": "", "photo": {"prefix": "https://igx.4sqi.net/img/user/", "suffix": "/blank_girl.png", "default": true}, "homeCity": "Singapore", "lists": {"groups": [{"items": [], "count": 2, "type": "created"}]}}, {"tips": {"count": 0}, "contact": {"facebook": "1226566977"}, "firstName": "Jackie", "gender": "male", "lastName": "Tan", "id": "9105031", "bio": "", "photo": {"prefix": "https://igx.4sqi.net/img/user/", "suffix": "/SEJAINMQVHPXSG5S.jpg"}, "homeCity": "jackietan_87@hotmail.com", "lists": {"groups": [{"items": [], "count": 2, "type": "created"}]}}, {"tips": {"count": 3}, "contact": {}, "firstName": "Danielle", "gender": "female", "lastName": "Ng", "id": "5401635", "bio": "", "photo": {"prefix": "https://igx.4sqi.net/img/user/", "suffix": "/JJYKYBJR3BSLNISL.jpg"}, "homeCity": "Singapore", "lists": {"groups": [{"items": [], "count": 2, "type": "created"}]}}, {"tips": {"count": 1}, "contact": {"facebook": "675228704"}, "firstName": "Marianna", "gender": "female", "lastName": "Kasmuri", "id": "3793180", "bio": "", "photo": {"prefix": "https://igx.4sqi.net/img/user/", "suffix": "/5DMABUPKSHIRWT51.jpg"}, "homeCity": "Singapore", "lists": {"groups": [{"items": [], "count": 2, "type": "created"}]}}, {"tips": {"count": 5}, "contact": {"facebook": "607424244"}, "firstName": "Muhd Shahrul", "gender": "male", "lastName": "Ameen", "id": "4586232", "bio": "", "photo": {"prefix": "https://igx.4sqi.net/img/user/", "suffix": "/V3I0E51K5CCNLR3M.jpg"}, "homeCity": "Singapore", "lists": {"groups": [{"items": [], "count": 2, "type": "created"}]}}, {"tips": {"count": 0}, "contact": {"facebook": "1355674792"}, "firstName": "Fyza", "gender": "female", "lastName": "Rulfy", "id": "3219169", "bio": "", "photo": {"prefix": "https://igx.4sqi.net/img/user/", "suffix": "/CNDKQ5LWRF021KQ2.jpg"}, "homeCity": "Singapore", "lists": {"groups": [{"items": [], "count": 2, "type": "created"}]}}, {"tips": {"count": 1}, "contact": {"twitter": "xianxiuling", "facebook": "596469470"}, "firstName": "Xiuling", "gender": "female", "lastName": "Xian", "id": "4490452", "bio": "", "photo": {"prefix": "https://igx.4sqi.net/img/user/", "suffix": "/YCDEL4GQOYGJ3LEB.jpg"}, "homeCity": "Singapore", "lists": {"groups": [{"items": [], "count": 2, "type": "created"}]}}, {"tips": {"count": 3}, "contact": {}, "firstName": "KENJI", "gender": "male", "lastName": "SAWAHII", "id": "34259273", "bio": "SINGLE AND AVAILABLE AND UNTOUCHABLE !!! WECHAT ID : KENJISAWAHII", "photo": {"prefix": "https://igx.4sqi.net/img/user/", "suffix": "/T05D5XHGIL2QEZAX.jpg"}, "homeCity": "KUALA LUMPUR", "lists": {"groups": [{"items": [], "count": 2, "type": "created"}]}}, {"tips": {"count": 0}, "contact": {}, "firstName": "Davin", "gender": "male", "lastName": "Chung", "id": "6953942", "bio": "", "photo": {"prefix": "https://igx.4sqi.net/img/user/", "suffix": "/E5WNYXOKXGYALW30.jpg"}, "homeCity": "Singapore", "lists": {"groups": [{"items": [], "count": 2, "type": "created"}]}}, {"tips": {"count": 0}, "contact": {"facebook": "1138720468"}, "firstName": "Richard", "gender": "male", "lastName": "Loo", "id": "13106754", "bio": "", "photo": {"prefix": "https://igx.4sqi.net/img/user/", "suffix": "/NEJUJ4ERHXV2CYFT.jpg"}, "homeCity": "Singapore", "lists": {"groups": [{"items": [], "count": 2, "type": "created"}]}}, {"tips": {"count": 5}, "contact": {"facebook": "871035065"}, "firstName": "Michael", "gender": "male", "lastName": "Ng", "id": "5826695", "bio": "", "photo": {"prefix": "https://igx.4sqi.net/img/user/", "suffix": "/2XWDZXJBANBGVPPC.jpg"}, "homeCity": "Singapore", "lists": {"groups": [{"items": [], "count": 2, "type": "created"}]}}, {"tips": {"count": 0}, "contact": {"facebook": "715440031"}, "firstName": "Coma", "gender": "female", "lastName": "Black", "id": "15778636", "bio": "", "photo": {"prefix": "https://igx.4sqi.net/img/user/", "suffix": "/5RJ0YPHXUX5VHDEU.jpg"}, "homeCity": "Singapore", "lists": {"groups": [{"items": [], "count": 2, "type": "created"}]}}, {"tips": {"count": 0}, "contact": {}, "firstName": "\u0f42\u0f44\u0f0b\u0f51\u0f42\u0f60\u0f0b", "gender": "male", "lastName": "\u0f42\u0f44\u0f0b\u0f51\u0f42\u0f60\u0f0b", "id": "25128932", "bio": "", "photo": {"prefix": "https://igx.4sqi.net/img/user/", "suffix": "/30V4F3D5IUNYIIXN.jpg"}, "homeCity": "Singapore ", "lists": {"groups": [{"items": [], "count": 2, "type": "created"}]}}, {"tips": {"count": 8}, "contact": {"facebook": "872750382"}, "firstName": "Sean", "gender": "male", "lastName": "Ng", "id": "10189302", "bio": "", "photo": {"prefix": "https://igx.4sqi.net/img/user/", "suffix": "/PC41A3UZKVPEMPIZ.jpg"}, "homeCity": "Singapore", "lists": {"groups": [{"items": [], "count": 2, "type": "created"}]}}, {"tips": {"count": 7}, "contact": {"twitter": "lzefier7", "facebook": "592237878"}, "firstName": "Dominic", "gender": "male", "lastName": "Cheong", "id": "5081200", "bio": "", "photo": {"prefix": "https://igx.4sqi.net/img/user/", "suffix": "/L1N4TH334DB34U41.jpg"}, "homeCity": "New York", "lists": {"groups": [{"items": [], "count": 2, "type": "created"}]}}, {"tips": {"count": 0}, "contact": {"facebook": "1157742520"}, "firstName": "Juliana", "gender": "female", "lastName": "Adams", "id": "3708110", "bio": "", "photo": {"prefix": "https://igx.4sqi.net/img/user/", "suffix": "/TN2TZCV3RSIMOXK2.jpg"}, "homeCity": "Singapore", "lists": {"groups": [{"items": [], "count": 2, "type": "created"}]}}, {"tips": {"count": 0}, "contact": {"facebook": "1506130362"}, "firstName": "Kay", "gender": "male", "lastName": "Tan Hui Neng", "id": "4764547", "bio": "", "photo": {"prefix": "https://igx.4sqi.net/img/user/", "suffix": "/H1Y4Z5PNYY5FC1LB.jpg"}, "homeCity": "Malaysia", "lists": {"groups": [{"items": [], "count": 2, "type": "created"}]}}, {"tips": {"count": 0}, "contact": {"facebook": "502381383"}, "firstName": "Pei Pei", "gender": "female", "lastName": "Tan", "id": "60150297", "bio": "", "photo": {"prefix": "https://igx.4sqi.net/img/user/", "suffix": "/CWIPCIKI01WPXOF5.jpg"}, "homeCity": "Singapore", "lists": {"groups": [{"items": [], "count": 2, "type": "created"}]}}, {"tips": {"count": 9}, "contact": {}, "firstName": "Chris", "gender": "none", "lastName": "Low", "id": "7255436", "bio": "", "photo": {"prefix": "https://igx.4sqi.net/img/user/", "suffix": "/TV3D00M1WVLNNSXK.jpg"}, "homeCity": "Singapore", "lists": {"groups": [{"items": [], "count": 2, "type": "created"}]}}, {"tips": {"count": 0}, "contact": {"twitter": "ticca_v", "facebook": "100001067626706"}, "firstName": "TicC \u2215\u0334\u0196", "gender": "female", "lastName": "ValovenoZz \u2215\u0334\u0196", "id": "9299624", "bio": "\u2661 @mr_draco \u2665", "photo": {"prefix": "https://igx.4sqi.net/img/user/", "suffix": "/H5C3PE1GF534PG2B.jpg"}, "homeCity": "", "lists": {"groups": [{"items": [], "count": 2, "type": "created"}]}}, {"tips": {"count": 0}, "contact": {"facebook": "627491511"}, "firstName": "Kar Mun", "gender": "female", "lastName": "Eu", "id": "16226668", "bio": "", "photo": {"prefix": "https://igx.4sqi.net/img/user/", "suffix": "/blank_girl.png", "default": true}, "homeCity": "Singapore", "lists": {"groups": [{"items": [], "count": 2, "type": "created"}]}}, {"tips": {"count": 0}, "contact": {"facebook": "595412465"}, "firstName": "Brenda", "gender": "female", "lastName": "Ng", "id": "13988066", "bio": "", "photo": {"prefix": "https://igx.4sqi.net/img/user/", "suffix": "/RUNNEZGUYJSX3ZEP.jpg"}, "homeCity": "Singapore", "lists": {"groups": [{"items": [], "count": 2, "type": "created"}]}}, {"tips": {"count": 8}, "contact": {"facebook": "836089833"}, "firstName": "Cindy", "gender": "female", "lastName": "Chang", "id": "5421359", "bio": "", "photo": {"prefix": "https://igx.4sqi.net/img/user/", "suffix": "/LHDJIIQYR5JJSC3V.jpg"}, "homeCity": "Singapore", "lists": {"groups": [{"items": [], "count": 2, "type": "created"}]}}, {"tips": {"count": 2}, "contact": {"facebook": "680841386"}, "firstName": "Felicia", "gender": "female", "lastName": "Boey", "id": "3982384", "bio": "", "photo": {"prefix": "https://igx.4sqi.net/img/user/", "suffix": "/FJSJMCFDBERMUFHA.jpg"}, "homeCity": "Singapore", "lists": {"groups": [{"items": [], "count": 2, "type": "created"}]}}, {"tips": {"count": 0}, "contact": {"twitter": "calista_jl", "facebook": "529838102"}, "firstName": "Calista", "gender": "female", "lastName": "Lee", "id": "6053752", "bio": "", "photo": {"prefix": "https://igx.4sqi.net/img/user/", "suffix": "/XREVXWMWBOEUMMXK.jpg"}, "homeCity": "Singapore", "lists": {"groups": [{"items": [], "count": 2, "type": "created"}]}}, {"tips": {"count": 3}, "contact": {}, "firstName": "Jamurai", "gender": "male", "lastName": "Shogun", "id": "7285205", "bio": "", "photo": {"prefix": "https://igx.4sqi.net/img/user/", "suffix": "/PQFMMKX44GOU1R2Y.jpg"}, "homeCity": "Singapore", "lists": {"groups": [{"items": [], "count": 2, "type": "created"}]}}, {"tips": {"count": 0}, "contact": {"facebook": "565770905"}, "firstName": "Davina", "gender": "female", "lastName": "Tham", "id": "24450874", "bio": "", "photo": {"prefix": "https://igx.4sqi.net/img/user/", "suffix": "/GXWWX4HAI42G0EIG.jpg"}, "homeCity": "Singapore", "lists": {"groups": [{"items": [], "count": 2, "type": "created"}]}}, {"tips": {"count": 0}, "contact": {"facebook": "724508268"}, "firstName": "lee", "gender": "female", "lastName": "kelly", "id": "4072875", "bio": "", "photo": {"prefix": "https://igx.4sqi.net/img/user/", "suffix": "/GZGOJ0JD02A52DYZ.jpg"}, "homeCity": "Singapore", "lists": {"groups": [{"items": [], "count": 2, "type": "created"}]}}, {"tips": {"count": 1}, "contact": {"facebook": "775395163"}, "firstName": "Patrick Aaron", "gender": "male", "lastName": "Seng", "id": "6653445", "bio": "", "photo": {"prefix": "https://igx.4sqi.net/img/user/", "suffix": "/KVR0Z1D5P3GR4HC2.jpg"}, "homeCity": "Singapore", "lists": {"groups": [{"items": [], "count": 2, "type": "created"}]}}, {"tips": {"count": 0}, "contact": {"facebook": "744385159"}, "firstName": "Joyclyn", "gender": "female", "lastName": "Tay", "id": "4084192", "bio": "", "photo": {"prefix": "https://igx.4sqi.net/img/user/", "suffix": "/NBMCVZI430G0AC5V.jpg"}, "homeCity": "Singapore", "lists": {"groups": [{"items": [], "count": 2, "type": "created"}]}}, {"tips": {"count": 0}, "contact": {"facebook": "100000476950494"}, "firstName": "Ray Ang", "gender": "male", "lastName": "Hock", "id": "13582073", "bio": "", "photo": {"prefix": "https://igx.4sqi.net/img/user/", "suffix": "/E3031OWUMRCJRYC3.jpg"}, "homeCity": "Singapore", "lists": {"groups": [{"items": [], "count": 2, "type": "created"}]}}, {"tips": {"count": 0}, "contact": {"facebook": "100000603492291"}, "firstName": "Devon", "gender": "female", "lastName": "Cheng", "id": "6016144", "bio": "", "photo": {"prefix": "https://igx.4sqi.net/img/user/", "suffix": "/5AFH3YFGVQ4OTZ4B.jpg"}, "homeCity": "Singapore", "lists": {"groups": [{"items": [], "count": 2, "type": "created"}]}}, {"tips": {"count": 2}, "contact": {"facebook": "551259807"}, "firstName": "Erik", "gender": "male", "lastName": "Tan", "id": "41894759", "bio": "www.elusyf2u.com/2028210\r\n\r\nThe Most Advance State of Art Anti Aging science \r\n\r\nwww.elusyf.com\r\nElusyf Cell ACTIVA SP 800\r\nAnti Aging Start from HERE..........", "photo": {"prefix": "https://igx.4sqi.net/img/user/", "suffix": "/I3CFUPXDNNYRP5K3.jpg"}, "homeCity": "Singapore", "lists": {"groups": [{"items": [], "count": 2, "type": "created"}]}}, {"tips": {"count": 0}, "contact": {"facebook": "574179697"}, "firstName": "Chew Ha", "gender": "none", "lastName": "Tan", "id": "6407230", "bio": "", "photo": {"prefix": "https://igx.4sqi.net/img/user/", "suffix": "/K3JJQGN3HSITYPGF.jpg"}, "homeCity": "Singapore", "lists": {"groups": [{"items": [], "count": 2, "type": "created"}]}}, {"tips": {"count": 1}, "contact": {"facebook": "100001458653882"}, "firstName": "Candy", "gender": "female", "lastName": "Thng", "id": "7440008", "bio": "", "photo": {"prefix": "https://igx.4sqi.net/img/user/", "suffix": "/V5Q3VO2CUHNANPSM.jpg"}, "homeCity": "Singapore", "lists": {"groups": [{"items": [], "count": 2, "type": "created"}]}}, {"tips": {"count": 0}, "contact": {"facebook": "1430691560"}, "firstName": "Sal", "gender": "female", "lastName": "M.A", "id": "7460127", "bio": "", "photo": {"prefix": "https://igx.4sqi.net/img/user/", "suffix": "/QA0T5JCIIASXLKRI.jpg"}, "homeCity": "Singapore", "lists": {"groups": [{"items": [], "count": 2, "type": "created"}]}}], "count": 75}, "checksum": "d062b6eed8afec76eb537a6ef563239ef78d40f0"}, "meta": {"requestId": "596620ba4434b96bff8baf7a", "code": 200}}